pyrcept/__init__.py
pyrcept/driver.py
pyrcept-0.0.1.dist-info/METADATA
pyrcept-0.0.1.dist-info/WHEEL
pyrcept-0.0.1.dist-info/licenses/LICENSE
pyrcept-0.0.1.dist-info/RECORD
