Metadata-Version: 2.4
Name: pyrcept
Version: 0.0.1
Summary: html/js based remote live plot viewing
Project-URL: Homepage, https://github.com/tscott-00/pyrcept
Author: Thomas A. Scott
License-File: LICENSE
Requires-Python: >=3.10
Requires-Dist: bottle
